_webm.cpython-313-aarch64-linux-gnu.so
include/webm/buffer_reader.h
include/webm/callback.h
include/webm/dom_types.h
include/webm/element.h
include/webm/file_reader.h
include/webm/id.h
include/webm/istream_reader.h
include/webm/reader.h
include/webm/status.h
include/webm/webm_parser.h
include/webm/common/webmids.h
include/webm/mkvmuxer/mkvmuxer.h
include/webm/mkvmuxer/mkvmuxertypes.h
include/webm/mkvmuxer/mkvmuxerutil.h
include/webm/mkvmuxer/mkvwriter.h
include/webm/mkvparser/mkvparser.h
include/webm/mkvparser/mkvreader.h
lib/libwebm.a
webm/__init__.py
libwebm_py-2025.1.0.dev0.dist-info/METADATA
libwebm_py-2025.1.0.dev0.dist-info/WHEEL
libwebm_py-2025.1.0.dev0.dist-info/RECORD
libwebm_py-2025.1.0.dev0.dist-info/licenses/LICENSE
