Metadata-Version: 2.4
Name: libwebm-py
Version: 2025.1.0.dev0
Summary: Python bindings for libwebm (via nanobind)
Author-Email: "Shiguredo Inc." <contact+pypi@shiguredo.jp>
License-Expression: Apache-2.0
License-File: LICENSE
Classifier: Programming Language :: Python :: 3
Classifier: Programming Language :: Python :: 3.11
Classifier: Programming Language :: Python :: 3.12
Classifier: Programming Language :: Python :: 3.13
Classifier: Programming Language :: C++
Classifier: Operating System :: MacOS :: MacOS X
Classifier: Operating System :: POSIX :: Linux
Classifier: Operating System :: Microsoft :: Windows
Project-URL: Source, https://github.com/shiguredo/libwebm-py
Project-URL: Discord, https://discord.gg/shiguredo
Requires-Python: >=3.11
